{
  "packages": [
    {
      "name": "arduinods4",
      "maintainer": "Flamethrower",
      "websiteURL": "https://github.com/Flamethr0wer",
      "help": {
        "online": "https://github.com/Flamethr0wer/ArduinoDS4"
      },
      "platforms": [
        {
          "name": "ArduinoDS4 AVR Boards",
          "architecture": "avr",
          "version": "1.0.0",
          "category": "Contributed",
          "url": "https://github.com/Flamethr0wer/ArduinoDS4-AVR/releases/download/v1.0.0/ArduinoDS4-avr-1.0.0.zip",
          "archiveFileName": "ArduinoDS4-avr-1.0.1.zip",
          "checksum": "SHA-256:358531d97cd6d42b388558c51b22bea5dd2540aa780a0c629e63345139b5c05a",
          "size": "27741362",
          "help": {
            "online": "https://github.com/Flamethr0wer/ArduinoDS4"
          },
          "boards": [
            {
              "name": "Arduino Leonardo as DS4"
            },
            {
              "name": "Arduino Leonardo ETH as DS4"
            },
            {
              "name": "Arduino Micro as DS4"
            },
            {
              "name": "Arduino Esplora as DS4"
            }
          ],
          "toolsDependencies": []
        }
      ]
    }
  ]
}
